politico_transcript_parser-0.0.2.dist-info/DESCRIPTION.rst
politico_transcript_parser-0.0.2.dist-info/METADATA
politico_transcript_parser-0.0.2.dist-info/RECORD
politico_transcript_parser-0.0.2.dist-info/WHEEL
politico_transcript_parser-0.0.2.dist-info/dependency_links.txt
politico_transcript_parser-0.0.2.dist-info/metadata.json
politico_transcript_parser-0.0.2.dist-info/top_level.txt
transcript_parser/__init__.py
