Metadata-Version: 2.0
Name: politico-transcript-parser
Version: 0.0.2
Summary: UNKNOWN
Home-page: https://github.com/The-Politico/politico-transcript-parser
Author: POLITICO interactive news
Author-email: interactives@politico.com
License: MIT
Platform: UNKNOWN
Classifier: Development Status :: 3 - Alpha
Classifier: Intended Audience :: Developers
Classifier: Intended Audience :: Information Technology
Classifier: License :: OSI Approved :: MIT License
Classifier: Operating System :: OS Independent
Classifier: Programming Language :: Python :: 3
Classifier: Programming Language :: Python :: 3.5
Classifier: Programming Language :: Python :: 3.6
Classifier: Topic :: Internet :: WWW/HTTP
Requires-Dist: html2text
Requires-Dist: copydoc
Provides-Extra: test
Requires-Dist: pytest; extra == 'test'
